pandas_mermaid/__init__.py
pandas_mermaid/converter.py
pandas_mermaid-0.2.0.dist-info/METADATA
pandas_mermaid-0.2.0.dist-info/WHEEL
pandas_mermaid-0.2.0.dist-info/top_level.txt
pandas_mermaid-0.2.0.dist-info/RECORD
