Metadata-Version: 2.4
Name: pandas-mermaid
Version: 0.2.0
Summary: Convert pandas DataFrame to Mermaid flowcharts
Author-email: raghuvasanthrao <k.s.raghuvsanthrao@gmail.com>
License: MIT
Project-URL: Homepage, https://github.com/raghuvasanthrao/pandas-mermaid
Requires-Python: >=3.7
Requires-Dist: pandas
